jamotools/__init__.py
jamotools/jamo/__init__.py
jamotools/jamo/hangul_utils.py
jamotools/jamo/unicode_table.py
jamotools/vector/__init__.py
jamotools/vector/rules.py
jamotools/vector/vector.py
jamotools-0.1.10.dist-info/DESCRIPTION.rst
jamotools-0.1.10.dist-info/METADATA
jamotools-0.1.10.dist-info/RECORD
jamotools-0.1.10.dist-info/WHEEL
jamotools-0.1.10.dist-info/metadata.json
jamotools-0.1.10.dist-info/top_level.txt
