Metadata-Version: 1.1
Name: jamotools
Version: 0.1.10
Summary: A library for Korean Jamo split and vectorize.
Home-page: https://github.com/HaebinShin/jamotools
Author: Haebin Shin
Author-email: sunsal0704@gmail.com
License: GPL
Platform: UNKNOWN
Classifier: Operating System :: OS Independent
Classifier: Intended Audience :: Developers
Classifier: Intended Audience :: Science/Research
Classifier: Programming Language :: Python :: 2
Classifier: Programming Language :: Python :: 2.7
Classifier: Programming Language :: Python :: 3
Classifier: Programming Language :: Python :: 3.4
Classifier: Programming Language :: Python :: 3.5
Classifier: Programming Language :: Python :: 3.6
Classifier: Topic :: Scientific/Engineering
Classifier: Topic :: Text Processing :: Linguistic
Classifier: Natural Language :: Korean
